{
  "Instance": "NL_FR_2_F",
  "Algorithm": "Heuristic",
  "Integer Master Problem Solution": {
    "Objective": 29294.3,
    "Variables": [
      {
        "weight":1,
        "nodes": [0, 1369, 1353, 1388, 1420, 1439, 1468, 1499, 1515, 1542, 1570, 1571, 1584, 1607, 1598, 1599, 1601, 1600, 1613, 1629, 1711, 1710, 1715, 1717, 1716, 1732, 1708, 1697, 1680, 1658, 1657, 1538, 1517, 0],
        "scheduled lines": [-1, -1, -1, -1, -1, -1, -1, -1, -1, -1, -1, -1, -1, -1, 3, -1, -1, -1, -1, -1, -1, -1, -1, -1, -1, -1, -1, 8, -1, -1, 8, -1]
      },
      {
        "weight":1,
        "nodes": [0, 1103, 1096, 1182, 1183, 1264, 1305, 1256, 1258, 1261, 1259, 1316, 1262, 1192, 1205, 1197, 1189, 1191, 1193, 1194, 1107, 1111, 1125, 1149, 1051, 0],
        "scheduled lines": [-1, -1, -1, -1, -1, -1, -1, -1, -1, 3, 8, -1, -1, -1, -1, -1, -1, -1, -1, -1, -1, -1, -1, -1]
      },
      {
        "weight":1,
        "nodes": [0, 1078, 1104, 1139, 1146, 1152, 1137, 1050, 1081, 1124, 1186, 1187, 1276, 1253, 1251, 1190, 1257, 1150, 1075, 1105, 963, 0],
        "scheduled lines": [-1, -1, -1, -1, -1, -1, -1, -1, -1, -1, -1, -1, -1, -1, -1, -1, -1, -1, -1, -1]
      },
      {
        "weight":1,
        "nodes": [0, 891, 959, 931, 954, 1082, 976, 1053, 918, 833, 914, 913, 895, 850, 851, 571, 651, 719, 730, 735, 791, 821, 813, 921, 0],
        "scheduled lines": [-1, -1, -1, -1, -1, -1, -1, -1, -1, -1, -1, -1, -1, -1, -1, -1, -1, -1, -1, -1, -1, -1, -1]
      },
      {
        "weight":1,
        "nodes": [0, 1017, 1068, 1138, 1162, 1363, 1359, 1339, 1330, 1469, 1471, 1488, 1485, 1513, 1512, 1509, 1470, 1459, 1391, 1384, 1319, 1325, 1260, 1296, 1302, 1297, 1122, 1164, 989, 0],
        "scheduled lines": [-1, -1, -1, -1, -1, -1, -1, -1, -1, -1, -1, -1, 3, -1, -1, -1, -1, -1, -1, -1, -1, -1, -1, -1, -1, -1, -1, -1]
      },
      {
        "weight":1,
        "nodes": [0, 1140, 1231, 1464, 1457, 1508, 1562, 1707, 1709, 1728, 1772, 1773, 1787, 1784, 1783, 1769, 1790, 1793, 1758, 1756, 1684, 1682, 1683, 0],
        "scheduled lines": [8, 8, -1, -1, -1, -1, -1, -1, -1, -1, -1, -1, -1, -1, -1, -1, -1, -1, 3, -1, -1, -1]
      },
      {
        "weight":1,
        "nodes": [0, 1217, 1389, 1334, 1355, 1405, 1387, 1500, 1503, 1525, 1635, 1639, 1628, 1641, 1659, 1637, 1636, 1640, 1642, 1643, 1652, 1653, 1225, 0],
        "scheduled lines": [-1, 8, -1, 8, -1, -1, -1, -1, -1, -1, -1, -1, -1, -1, -1, -1, -1, -1, -1, -1, -1, -1]
      },
      {
        "weight":1,
        "nodes": [0, 811, 724, 835, 771, 840, 834, 945, 906, 925, 1013, 1006, 957, 1055, 1057, 1015, 911, 940, 0],
        "scheduled lines": [-1, -1, -1, -1, -1, -1, -1, -1, -1, -1, -1, -1, -1, 8, -1, -1, -1]
      },
      {
        "weight":1,
        "nodes": [0, 998, 905, 873, 888, 870, 854, 923, 829, 831, 830, 786, 800, 785, 801, 806, 860, 849, 882, 858, 872, 848, 972, 949, 966, 980, 979, 0],
        "scheduled lines": [-1, -1, -1, -1, -1, -1, -1, -1, 3, -1, -1, -1, -1, -1, 3, -1, -1, -1, -1, -1, -1, -1, -1, -1, -1, -1]
      },
      {
        "weight":1,
        "nodes": [0, 825, 570, 639, 576, 685, 572, 681, 580, 787, 707, 797, 807, 789, 783, 1032, 1031, 941, 943, 944, 946, 1033, 962, 1043, 1094, 1113, 1062, 1063, 1093, 983, 916, 0],
        "scheduled lines": [-1, -1, -1, -1, -1, -1, -1, -1, -1, -1, -1, -1, -1, -1, -1, 8, -1, -1, -1, -1, -1, -1, -1, -1, -1, -1, -1, -1, -1, -1]
      },
      {
        "weight":1,
        "nodes": [0, 1106, 1110, 1095, 1171, 1184, 1181, 1245, 1232, 1188, 1265, 1309, 1288, 1280, 1282, 1306, 1321, 1320, 1329, 1308, 1300, 1348, 1358, 1360, 1263, 1350, 0],
        "scheduled lines": [-1, -1, -1, -1, -1, -1, -1, -1, -1, -1, -1, -1, -1, -1, -1, -1, -1, -1, -1, -1, 8, -1, 3, -1, -1]
      },
      {
        "weight":1,
        "nodes": [0, 1354, 1414, 1361, 1492, 1489, 1501, 1531, 1572, 1583, 1573, 1603, 1575, 1592, 1587, 1604, 1545, 1546, 1466, 1423, 1349, 1432, 1351, 1277, 1201, 1074, 0],
        "scheduled lines": [-1, -1, -1, -1, -1, -1, -1, -1, -1, -1, -1, -1, 3, -1, 3, 9, -1, -1, -1, -1, -1, -1, -1, -1, -1]
      },
      {
        "weight":1,
        "nodes": [0, 995, 999, 793, 798, 778, 759, 650, 648, 734, 720, 743, 762, 744, 738, 712, 706, 756, 760, 969, 0],
        "scheduled lines": [-1, 8, 8, -1, -1, -1, -1, -1, -1, -1, -1, -1, -1, -1, -1, -1, -1, 3, -1]
      },
      {
        "weight":1,
        "nodes": [0, 1018, 713, 669, 668, 666, 605, 603, 596, 607, 589, 610, 595, 593, 608, 601, 598, 597, 604, 636, 691, 739, 867, 1019, 985, 0],
        "scheduled lines": [8, -1, 8, -1, -1, -1, -1, -1, -1, -1, -1, -1, -1, -1, -1, -1, -1, -1, -1, -1, -1, -1, -1, -1]
      },
      {
        "weight":1,
        "nodes": [0, 1465, 1567, 1568, 1611, 1700, 1750, 1751, 1752, 1775, 1774, 1782, 1776, 0],
        "scheduled lines": [-1, -1, -1, -1, -1, 8, 9, -1, -1, -1, 8, -1]
      },
      {
        "weight":1,
        "nodes": [0, 952, 953, 904, 815, 814, 986, 0],
        "scheduled lines": [8, -1, -1, 3, -1, 3]
      },
      {
        "weight":1,
        "nodes": [0, 1115, 1141, 1275, 1373, 1421, 1408, 1416, 1413, 1434, 1312, 1236, 1235, 1234, 1169, 965, 997, 0],
        "scheduled lines": [-1, -1, -1, -1, -1, -1, -1, -1, -1, -1, -1, -1, -1, -1, -1, -1]
      },
      {
        "weight":1,
        "nodes": [0, 990, 1069, 1042, 922, 737, 613, 600, 609, 599, 577, 469, 343, 297, 300, 298, 295, 299, 296, 236, 257, 170, 161, 231, 235, 254, 250, 252, 256, 0],
        "scheduled lines": [-1, -1, -1, -1, -1, -1, -1, -1, -1, -1, -1, -1, -1, -1, -1, -1, -1, -1, -1, -1, -1, -1, -1, -1, -1, -1, -1, -1]
      },
      {
        "weight":1,
        "nodes": [0, 1039, 1072, 880, 960, 935, 837, 842, 838, 839, 822, 748, 773, 812, 781, 659, 661, 568, 652, 628, 663, 687, 672, 692, 688, 788, 884, 939, 0],
        "scheduled lines": [-1, -1, -1, -1, -1, -1, -1, 3, -1, -1, -1, -1, -1, -1, -1, -1, -1, -1, -1, -1, -1, -1, -1, -1, -1, 8, -1]
      },
      {
        "weight":1,
        "nodes": [0, 805, 871, 546, 529, 372, 381, 209, 198, 222, 216, 210, 219, 224, 221, 212, 208, 218, 213, 217, 163, 251, 253, 255, 473, 772, 987, 970, 0],
        "scheduled lines": [-1, -1, -1, -1, -1, -1, -1, -1, -1, -1, -1, -1, -1, -1, -1, -1, -1, -1, -1, -1, -1, -1, -1, -1, -1, -1, -1]
      },
      {
        "weight":1,
        "nodes": [0, 802, 715, 641, 622, 538, 531, 554, 561, 682, 701, 658, 702, 637, 634, 633, 643, 582, 629, 630, 606, 602, 667, 868, 991, 0],
        "scheduled lines": [9, -1, -1, -1, -1, -1, -1, -1, -1, -1, -1, -1, -1, -1, -1, -1, -1, -1, -1, 3, -1, -1, -1, -1]
      },
      {
        "weight":1,
        "nodes": [0, 1030, 929, 903, 890, 933, 961, 928, 934, 1023, 1011, 927, 1014, 1035, 1034, 1059, 1009, 1010, 1049, 1008, 1047, 1092, 1114, 1151, 1121, 1118, 1108, 1076, 1090, 1089, 1088, 0],
        "scheduled lines": [-1, -1, -1, -1, -1, -1, -1, -1, -1, 8, -1, -1, -1, -1, -1, -1, 3, -1, -1, -1, -1, -1, -1, -1, -1, -1, -1, 8, -1, 8]
      },
      {
        "weight":1,
        "nodes": [0, 1038, 1064, 1027, 1001, 973, 951, 1004, 993, 1000, 942, 889, 881, 863, 930, 896, 919, 920, 992, 950, 955, 994, 1002, 1005, 1003, 1028, 1012, 1022, 1071, 967, 958, 1073, 1058, 1007, 974, 0],
        "scheduled lines": [-1, -1, -1, -1, -1, -1, -1, -1, -1, -1, -1, -1, -1, -1, -1, -1, -1, -1, -1, -1, -1, -1, -1, -1, -1, -1, -1, -1, -1, -1, -1, 3, -1, -1]
      },
      {
        "weight":1,
        "nodes": [0, 1040, 874, 932, 875, 742, 765, 749, 690, 585, 632, 649, 645, 578, 581, 621, 620, 619, 612, 575, 642, 722, 718, 0],
        "scheduled lines": [-1, -1, -1, -1, -1, -1, -1, -1, -1, -1, -1, -1, -1, -1, -1, -1, -1, -1, -1, -1, -1, -1]
      },
      {
        "weight":1,
        "nodes": [0, 1455, 1444, 1476, 1519, 1561, 1577, 1578, 1586, 1588, 1582, 1615, 1595, 1579, 1594, 1581, 1602, 1597, 1580, 1606, 1596, 1590, 0],
        "scheduled lines": [-1, -1, 9, -1, -1, -1, -1, -1, -1, -1, -1, -1, -1, -1, -1, -1, -1, -1, -1, -1, -1]
      },
      {
        "weight":1,
        "nodes": [0, 564, 565, 537, 563, 541, 558, 536, 640, 534, 539, 532, 533, 526, 559, 560, 618, 665, 689, 660, 736, 751, 823, 747, 754, 841, 907, 1077, 1060, 1016, 1025, 1029, 937, 0],
        "scheduled lines": [-1, -1, -1, -1, -1, -1, -1, -1, -1, -1, -1, -1, -1, -1, -1, -1, -1, -1, -1, -1, -1, -1, -1, -1, -1, -1, -1, -1, -1, -1, -1, -1]
      },
      {
        "weight":1,
        "nodes": [0, 319, 271, 220, 214, 223, 211, 215, 33, 11, 9, 3, 7, 4, 10, 5, 6, 8, 23, 22, 26, 81, 130, 132, 138, 143, 442, 0],
        "scheduled lines": [-1, -1, -1, -1, -1, -1, -1, -1, -1, -1, -1, -1, -1, -1, -1, -1, -1, -1, -1, -1, -1, -1, -1, -1, -1, -1]
      },
      {
        "weight":1,
        "nodes": [0, 1126, 1160, 1195, 1249, 1356, 1386, 1393, 1406, 1412, 1477, 1440, 1473, 1493, 1504, 1461, 1463, 1417, 1480, 1400, 1397, 1385, 1299, 1301, 1298, 1239, 1238, 1266, 1178, 1177, 1158, 1196, 1159, 1101, 0],
        "scheduled lines": [-1, 8, -1, -1, -1, -1, 8, -1, -1, -1, -1, -1, -1, -1, -1, -1, -1, -1, -1, -1, -1, -1, -1, -1, -1, -1, -1, -1, -1, -1, -1, -1, -1]
      },
      {
        "weight":1,
        "nodes": [0, 1206, 1168, 1243, 1242, 1173, 1174, 1267, 1335, 1422, 1445, 1437, 1435, 1511, 1564, 1565, 1563, 1566, 1681, 1685, 1634, 1633, 1576, 1557, 1341, 0],
        "scheduled lines": [-1, -1, -1, -1, -1, -1, 8, -1, -1, -1, -1, -1, -1, -1, 8, -1, -1, -1, -1, -1, -1, -1, -1, -1]
      },
      {
        "weight":1,
        "nodes": [0, 1482, 1481, 1490, 1478, 1638, 1645, 1644, 1646, 1649, 1679, 1647, 1648, 1626, 1632, 1627, 1589, 1585, 1610, 1591, 1605, 1609, 1574, 1528, 1524, 1541, 1526, 1502, 1498, 1494, 1402, 1442, 1430, 1431, 0],
        "scheduled lines": [-1, -1, -1, -1, 8, -1, -1, 8, -1, 8, -1, -1, -1, 8, -1, -1, -1, -1, -1, -1, 8, -1, -1, -1, -1, -1, -1, -1, -1, -1, -1, -1, -1]
      },
      {
        "weight":1,
        "nodes": [0, 1084, 1085, 1112, 1056, 1144, 1180, 1211, 1210, 1281, 1315, 1278, 1307, 1284, 1294, 1324, 1289, 1287, 1290, 1292, 1293, 1322, 1241, 1208, 0],
        "scheduled lines": [-1, -1, -1, -1, -1, -1, 9, -1, -1, -1, -1, -1, -1, -1, -1, -1, -1, -1, -1, -1, 8, -1, -1]
      },
      {
        "weight":1,
        "nodes": [0, 988, 982, 981, 877, 876, 862, 869, 853, 865, 845, 866, 799, 917, 818, 826, 683, 696, 694, 695, 697, 796, 794, 779, 898, 864, 855, 846, 861, 761, 763, 964, 0],
        "scheduled lines": [8, -1, -1, -1, -1, -1, -1, 8, -1, -1, -1, -1, -1, -1, -1, 8, -1, -1, -1, -1, -1, -1, -1, -1, -1, -1, -1, -1, 9, 3, 8]
      },
      {
        "weight":1,
        "nodes": [0, 1109, 1116, 1143, 1142, 1147, 1227, 1224, 1229, 1271, 1362, 1364, 1401, 1424, 1409, 1425, 1410, 1411, 1433, 1365, 1403, 1407, 1394, 1399, 1221, 1220, 1222, 978, 1020, 0],
        "scheduled lines": [-1, -1, -1, -1, -1, -1, 8, -1, -1, -1, -1, -1, 9, -1, -1, -1, 8, -1, -1, -1, -1, 8, -1, -1, -1, -1, -1, -1]
      },
      {
        "weight":1,
        "nodes": [0, 859, 852, 776, 817, 782, 795, 777, 804, 740, 780, 733, 725, 790, 732, 803, 908, 885, 879, 1036, 938, 1024, 1026, 1052, 996, 0],
        "scheduled lines": [-1, -1, -1, -1, -1, -1, -1, -1, -1, -1, -1, -1, -1, -1, -1, -1, -1, -1, -1, -1, 8, -1, -1, -1]
      },
      {
        "weight":1,
        "nodes": [0, 587, 646, 592, 588, 544, 434, 429, 445, 439, 444, 438, 435, 431, 436, 430, 673, 745, 755, 836, 0],
        "scheduled lines": [-1, -1, -1, -1, 9, -1, -1, 8, -1, -1, -1, -1, -1, -1, -1, -1, -1, -1, -1]
      },
      {
        "weight":1,
        "nodes": [0, 1398, 1429, 1467, 1377, 1472, 1484, 1491, 1486, 1475, 1451, 1452, 1462, 1460, 1426, 1327, 1304, 1317, 1310, 1326, 1230, 1295, 1380, 1269, 1268, 0],
        "scheduled lines": [-1, -1, -1, -1, -1, -1, -1, -1, -1, -1, -1, -1, -1, -1, -1, -1, -1, -1, -1, -1, -1, -1, -1, -1]
      },
      {
        "weight":1,
        "nodes": [0, 1079, 1145, 1102, 1099, 1098, 1100, 1136, 1199, 1198, 1200, 1218, 1216, 1176, 1155, 1172, 1129, 1156, 0],
        "scheduled lines": [-1, -1, -1, -1, -1, -1, -1, -1, -1, -1, -1, -1, 8, -1, -1, -1, -1]
      },
      {
        "weight":1,
        "nodes": [0, 1163, 1175, 1167, 1165, 1166, 1248, 1213, 1219, 1246, 1340, 1507, 1543, 1529, 1534, 1530, 1551, 1556, 1552, 1616, 1614, 1612, 1608, 1523, 1522, 1495, 1458, 1303, 1127, 1119, 0],
        "scheduled lines": [8, 8, -1, -1, -1, -1, 9, -1, -1, -1, 8, -1, -1, 9, -1, -1, 9, -1, -1, 8, -1, -1, -1, -1, -1, -1, 8, -1, -1]
      },
      {
        "weight":1,
        "nodes": [0, 625, 623, 614, 590, 624, 573, 615, 566, 579, 626, 586, 616, 574, 433, 437, 432, 443, 440, 441, 705, 647, 638, 711, 824, 971, 975, 0],
        "scheduled lines": [8, -1, -1, -1, -1, -1, -1, -1, -1, -1, -1, -1, -1, -1, -1, -1, -1, -1, -1, -1, -1, -1, -1, 3, -1, -1]
      },
      {
        "weight":1,
        "nodes": [1, 1366, 1352, 1497, 1496, 1549, 1593, 1619, 1664, 1665, 1662, 1663, 1661, 1676, 1449, 1450, 1342, 1346, 1],
        "scheduled lines": [0, 0, 12, 11, 0, 0, -1, -1, 7, -1, -1, -1, -1, 4, 4, 0, 4]
      },
      {
        "weight":1,
        "nodes": [1, 1438, 1441, 1514, 1548, 1618, 1701, 1698, 1623, 1617, 1506, 1374, 1415, 1368, 1367, 1375, 1323, 1337, 1345, 1],
        "scheduled lines": [-1, -1, -1, -1, -1, -1, 4, 0, -1, 11, 4, 4, -1, -1, -1, -1, -1, -1]
      },
      {
        "weight":1,
        "nodes": [1, 1718, 1737, 1765, 1766, 1796, 1761, 1735, 1734, 1733, 1727, 1730, 1713, 1714, 1704, 1620, 1569, 1558, 1544, 1547, 1535, 1532, 1],
        "scheduled lines": [12, -1, -1, 12, -1, -1, -1, -1, -1, -1, 7, -1, -1, -1, 7, -1, -1, -1, 0, -1, -1]
      },
      {
        "weight":1,
        "nodes": [1, 1254, 1202, 1226, 1131, 1135, 1133, 1083, 1117, 1044, 1045, 1048, 899, 887, 857, 1170, 1212, 1215, 1250, 1],
        "scheduled lines": [0, 11, 4, -1, 4, 11, 7, -1, -1, -1, 0, 4, 0, -1, 0, -1, 0, 4]
      },
      {
        "weight":1,
        "nodes": [1, 1396, 1456, 1527, 1518, 1520, 1516, 1540, 1559, 1560, 1621, 1655, 1699, 1671, 1673, 1667, 1677, 1696, 1],
        "scheduled lines": [0, -1, -1, -1, -1, 11, -1, -1, -1, 5, 5, -1, -1, 11, 5, -1, 7]
      },
      {
        "weight":1,
        "nodes": [1, 1666, 1678, 1675, 1723, 1742, 1740, 1739, 1741, 1753, 1749, 1755, 1726, 1712, 1702, 1686, 1695, 1674, 1],
        "scheduled lines": [11, -1, 0, 12, 11, -1, 0, 0, 5, -1, 5, -1, 0, 12, 5, -1, -1]
      },
      {
        "weight":1,
        "nodes": [1, 1754, 1757, 1764, 1778, 1794, 1798, 1797, 1791, 1771, 1781, 1785, 1786, 1779, 1724, 1689, 1692, 1687, 1691, 1688, 1694, 1],
        "scheduled lines": [-1, 0, -1, -1, 5, 0, -1, -1, -1, 11, -1, -1, -1, -1, -1, -1, -1, -1, -1, -1]
      },
      {
        "weight":1,
        "nodes": [1, 1331, 1357, 1314, 1371, 1436, 1454, 1448, 1447, 1428, 1427, 1474, 1505, 1510, 1521, 1550, 1537, 1536, 1539, 1622, 1651, 1654, 1656, 1660, 1631, 1555, 1533, 1553, 1554, 1],
        "scheduled lines": [-1, 11, -1, -1, -1, -1, -1, -1, 12, 11, 11, 11, -1, -1, -1, -1, -1, 5, -1, -1, -1, -1, 12, -1, -1, -1, -1, -1]
      },
      {
        "weight":1,
        "nodes": [1, 1625, 1650, 1668, 1669, 1672, 1670, 1706, 1738, 1746, 1745, 1747, 1759, 1763, 1795, 1792, 1789, 1768, 1767, 1744, 1729, 1731, 1721, 1722, 1720, 1719, 1703, 1],
        "scheduled lines": [0, 11, -1, -1, 12, -1, 0, 11, -1, -1, -1, -1, -1, -1, -1, -1, 11, -1, 12, -1, -1, 11, -1, 11, 11, -1]
      },
      {
        "weight":1,
        "nodes": [1, 1209, 1286, 1157, 1132, 1134, 1070, 1041, 1046, 897, 893, 808, 847, 809, 810, 767, 727, 766, 820, 1087, 1086, 1128, 1120, 1130, 1244, 1233, 1273, 1336, 1378, 1370, 1328, 1383, 1],
        "scheduled lines": [0, -1, 11, 0, 0, -1, 0, 11, 11, 0, 0, -1, -1, 11, -1, 0, -1, -1, -1, 5, 0, -1, -1, -1, 11, -1, -1, 11, -1, 11, 11]
      },
      {
        "weight":1,
        "nodes": [1, 1153, 1148, 1154, 1097, 1067, 936, 856, 828, 819, 680, 698, 728, 746, 752, 886, 901, 894, 902, 892, 900, 1214, 1207, 1228, 1223, 1],
        "scheduled lines": [0, 0, 5, 11, 5, 11, -1, -1, -1, -1, 7, -1, 11, -1, -1, -1, -1, -1, -1, -1, 11, -1, 11, -1]
      },
      {
        "weight":1,
        "nodes": [1, 1624, 1630, 1705, 1725, 1736, 1777, 1788, 1780, 1770, 1762, 1760, 1748, 1743, 1690, 1693, 1487, 1],
        "scheduled lines": [-1, -1, -1, -1, -1, -1, 11, 0, -1, -1, 0, 12, 7, -1, -1, 7]
      },
      {
        "weight":1,
        "nodes": [1, 1204, 1203, 1240, 1291, 1347, 1332, 1379, 1382, 1418, 1376, 1419, 1446, 1381, 1392, 1372, 1390, 1395, 1344, 1333, 1338, 1343, 1],
        "scheduled lines": [-1, 0, -1, -1, 12, -1, 0, 12, -1, -1, -1, 11, 0, 12, -1, 0, -1, -1, 0, 7, -1]
      },
      {
        "weight":1,
        "nodes": [2, 484, 956, 1123, 1179, 1252, 1247, 1318, 1272, 1279, 1061, 1037, 1065, 912, 547, 552, 553, 417, 403, 2],
        "scheduled lines": [-1, 6, -1, -1, -1, -1, -1, -1, -1, -1, -1, -1, -1, -1, -1, -1, -1, -1]
      },
      {
        "weight":1,
        "nodes": [2, 485, 483, 617, 635, 700, 723, 741, 878, 947, 1021, 1080, 1091, 1054, 909, 926, 924, 708, 515, 464, 363, 367, 2],
        "scheduled lines": [-1, -1, -1, 2, -1, -1, -1, -1, -1, -1, 2, -1, -1, -1, 2, -1, -1, -1, -1, -1, -1]
      },
      {
        "weight":1,
        "nodes": [2, 306, 275, 244, 285, 282, 200, 187, 127, 151, 144, 133, 126, 148, 142, 117, 114, 122, 113, 110, 72, 70, 76, 69, 166, 165, 173, 172, 2],
        "scheduled lines": [-1, -1, -1, -1, -1, -1, -1, -1, -1, -1, -1, -1, -1, -1, -1, 2, -1, -1, -1, -1, -1, -1, -1, -1, -1, -1, -1]
      },
      {
        "weight":1,
        "nodes": [2, 371, 379, 384, 400, 393, 410, 428, 530, 499, 408, 406, 407, 374, 248, 272, 245, 364, 311, 288, 274, 273, 125, 97, 190, 2],
        "scheduled lines": [2, -1, -1, -1, 10, -1, -1, -1, -1, -1, -1, -1, -1, -1, -1, -1, -1, -1, -1, -1, -1, -1, -1, -1]
      },
      {
        "weight":1,
        "nodes": [2, 317, 333, 312, 247, 246, 266, 226, 270, 263, 241, 188, 98, 49, 99, 78, 86, 85, 71, 63, 75, 157, 301, 302, 336, 2],
        "scheduled lines": [-1, -1, -1, -1, -1, -1, -1, -1, -1, -1, -1, -1, -1, -1, -1, -1, 10, 10, -1, -1, -1, -1, 10, -1]
      },
      {
        "weight":1,
        "nodes": [2, 488, 480, 557, 555, 569, 644, 545, 662, 693, 710, 714, 654, 671, 627, 413, 427, 394, 388, 2],
        "scheduled lines": [-1, -1, -1, -1, -1, 2, -1, -1, -1, -1, -1, -1, -1, -1, -1, -1, -1, -1]
      },
      {
        "weight":1,
        "nodes": [2, 342, 340, 355, 377, 328, 378, 383, 380, 423, 420, 448, 452, 509, 506, 507, 504, 451, 477, 493, 496, 475, 489, 502, 525, 517, 518, 519, 520, 2],
        "scheduled lines": [-1, -1, -1, -1, -1, -1, -1, -1, -1, -1, -1, -1, -1, -1, -1, -1, -1, -1, -1, -1, -1, -1, -1, -1, -1, -1, -1, -1]
      },
      {
        "weight":1,
        "nodes": [2, 356, 347, 456, 459, 462, 457, 467, 345, 337, 294, 2],
        "scheduled lines": [-1, -1, -1, -1, -1, -1, -1, -1, -1, -1]
      },
      {
        "weight":1,
        "nodes": [2, 238, 203, 101, 38, 35, 13, 12, 14, 25, 20, 32, 30, 29, 45, 44, 34, 56, 50, 54, 52, 59, 62, 51, 175, 2],
        "scheduled lines": [-1, -1, -1, -1, -1, -1, -1, -1, -1, -1, -1, -1, -1, -1, -1, 2, -1, 10, -1, -1, 10, 10, -1, -1]
      },
      {
        "weight":1,
        "nodes": [2, 307, 232, 233, 240, 185, 237, 193, 234, 145, 192, 160, 103, 92, 91, 2],
        "scheduled lines": [-1, -1, -1, -1, -1, -1, -1, -1, -1, -1, -1, 2, -1, -1]
      },
      {
        "weight":1,
        "nodes": [2, 548, 535, 524, 684, 676, 584, 679, 750, 816, 764, 729, 656, 674, 675, 717, 653, 678, 657, 655, 514, 418, 2],
        "scheduled lines": [2, -1, -1, -1, -1, -1, -1, -1, 2, 2, -1, -1, -1, -1, -1, -1, -1, -1, -1, -1, -1]
      },
      {
        "weight":1,
        "nodes": [2, 321, 358, 346, 335, 339, 422, 409, 463, 426, 395, 391, 2],
        "scheduled lines": [-1, -1, -1, -1, -1, 2, -1, -1, -1, -1, -1]
      },
      {
        "weight":1,
        "nodes": [2, 508, 505, 542, 550, 591, 543, 522, 491, 490, 503, 412, 399, 310, 181, 180, 136, 137, 139, 2],
        "scheduled lines": [-1, -1, -1, -1, -1, -1, -1, -1, -1, -1, -1, -1, -1, -1, -1, -1, -1, -1]
      },
      {
        "weight":1,
        "nodes": [2, 243, 189, 228, 202, 186, 128, 2],
        "scheduled lines": [-1, -1, -1, -1, -1, -1]
      },
      {
        "weight":1,
        "nodes": [2, 784, 843, 915, 910, 948, 977, 968, 1161, 1274, 1283, 1443, 1453, 1483, 1479, 1404, 1311, 1313, 1285, 1185, 1237, 1255, 1270, 1066, 984, 883, 757, 631, 470, 361, 2],
        "scheduled lines": [-1, -1, -1, -1, -1, -1, -1, -1, -1, -1, 2, -1, -1, -1, -1, -1, -1, -1, -1, -1, -1, -1, -1, -1, -1, -1, -1, 2, -1]
      },
      {
        "weight":1,
        "nodes": [2, 278, 258, 283, 194, 199, 230, 206, 207, 286, 322, 308, 141, 131, 154, 115, 135, 152, 182, 195, 191, 164, 168, 162, 167, 155, 178, 171, 239, 2],
        "scheduled lines": [-1, -1, -1, -1, -1, -1, -1, -1, -1, -1, -1, -1, -1, -1, 10, -1, -1, -1, -1, -1, -1, -1, -1, -1, -1, -1, -1, -1]
      },
      {
        "weight":1,
        "nodes": [2, 259, 227, 229, 201, 196, 197, 158, 156, 183, 150, 121, 118, 120, 107, 108, 111, 109, 119, 124, 82, 73, 74, 123, 116, 147, 149, 140, 134, 205, 292, 2],
        "scheduled lines": [-1, -1, -1, -1, -1, -1, -1, -1, -1, -1, -1, -1, -1, -1, -1, -1, -1, -1, -1, -1, -1, -1, -1, -1, -1, -1, -1, -1, -1, -1]
      },
      {
        "weight":1,
        "nodes": [2, 316, 344, 360, 309, 280, 313, 405, 411, 338, 225, 262, 261, 249, 260, 264, 184, 83, 79, 67, 60, 65, 77, 64, 43, 66, 41, 42, 37, 318, 2],
        "scheduled lines": [2, -1, -1, -1, 10, -1, -1, -1, -1, -1, -1, -1, -1, 10, -1, -1, -1, 2, -1, -1, -1, -1, -1, -1, -1, -1, -1, -1, 10]
      },
      {
        "weight":1,
        "nodes": [2, 277, 279, 204, 169, 112, 80, 47, 48, 31, 18, 27, 17, 15, 19, 16, 21, 24, 28, 36, 46, 39, 40, 53, 61, 58, 55, 57, 177, 2],
        "scheduled lines": [-1, -1, -1, -1, -1, -1, -1, -1, -1, -1, 6, -1, -1, -1, -1, -1, -1, -1, -1, -1, -1, -1, -1, -1, -1, -1, -1, -1]
      },
      {
        "weight":1,
        "nodes": [2, 482, 516, 523, 567, 562, 583, 664, 699, 792, 721, 726, 677, 670, 703, 768, 769, 753, 844, 832, 774, 731, 770, 775, 827, 716, 709, 704, 686, 2],
        "scheduled lines": [-1, -1, -1, -1, 10, -1, -1, -1, -1, -1, 6, -1, -1, 2, -1, -1, -1, -1, -1, -1, -1, -1, -1, -1, -1, -1, 2, -1]
      },
      {
        "weight":1,
        "nodes": [2, 449, 510, 468, 611, 551, 594, 556, 758, 528, 527, 501, 511, 549, 512, 513, 453, 481, 421, 460, 419, 425, 373, 375, 392, 385, 349, 352, 357, 354, 331, 2],
        "scheduled lines": [-1, -1, -1, -1, -1, -1, -1, -1, -1, -1, -1, -1, -1, -1, 2, -1, -1, -1, -1, -1, -1, -1, -1, -1, -1, -1, -1, -1, -1, -1]
      },
      {
        "weight":1,
        "nodes": [2, 269, 93, 94, 96, 104, 102, 106, 95, 100, 105, 68, 90, 84, 88, 87, 89, 129, 159, 153, 176, 146, 179, 174, 242, 305, 353, 2],
        "scheduled lines": [-1, -1, -1, -1, -1, -1, -1, -1, -1, -1, 10, -1, -1, -1, -1, -1, -1, -1, -1, -1, -1, -1, -1, -1, -1, -1]
      },
      {
        "weight":1,
        "nodes": [2, 291, 268, 267, 265, 289, 287, 276, 324, 325, 387, 386, 450, 474, 478, 494, 498, 492, 472, 521, 495, 497, 454, 461, 455, 370, 2],
        "scheduled lines": [-1, -1, 10, -1, -1, -1, -1, -1, -1, -1, -1, -1, -1, -1, -1, -1, -1, -1, -1, -1, -1, -1, -1, -1, -1]
      },
      {
        "weight":1,
        "nodes": [2, 341, 382, 369, 466, 465, 458, 471, 540, 500, 486, 479, 487, 476, 446, 416, 404, 424, 414, 447, 398, 401, 415, 351, 389, 366, 390, 402, 2],
        "scheduled lines": [-1, 2, -1, -1, -1, -1, 2, -1, -1, -1, 10, -1, -1, -1, -1, -1, -1, -1, -1, 2, -1, -1, -1, -1, -1, -1, -1]
      },
      {
        "weight":1,
        "nodes": [2, 284, 323, 315, 314, 320, 281, 290, 304, 330, 348, 350, 326, 332, 329, 303, 293, 327, 334, 365, 396, 397, 362, 376, 359, 368, 2],
        "scheduled lines": [-1, -1, -1, 10, 10, -1, -1, -1, 10, -1, -1, -1, -1, -1, -1, -1, -1, -1, -1, -1, -1, -1, -1, -1, -1]
      }
    ]
  }
}