{

"Instance": "BE_WE_4_R",
  "Algorithm": "Heuristic",
  "Integer Master Problem Solution": {
    "Objective": 3467.78,
    "Variables": [
      {
        "weight":1,
        "nodes": [0, 70, 27, 61, 131, 31, 4, 63, 14, 12, 26, 43, 76, 129, 0],
        "scheduled lines": [-1, -1, -1, -1, -1, -1, -1, -1, -1, -1, 9, -1, -1]
      },
      {
        "weight":1,
        "nodes": [0, 59, 83, 40, 120, 71, 118, 85, 128, 37, 34, 46, 19, 21, 0],
        "scheduled lines": [-1, -1, -1, -1, -1, -1, -1, -1, -1, -1, -1, -1, -1]
      },
      {
        "weight":1,
        "nodes": [0, 9, 127, 97, 98, 62, 104, 47, 49, 56, 79, 105, 30, 67, 20, 106, 0],
        "scheduled lines": [-1, -1, 27, -1, -1, -1, -1, 27, 27, -1, -1, -1, -1, -1, -1]
      },
      {
        "weight":1,
        "nodes": [0, 119, 117, 133, 29, 111, 89, 58, 39, 88, 0],
        "scheduled lines": [-1, -1, -1, -1, -1, -1, -1, -1, -1]
      },
      {
        "weight":1,
        "nodes": [1, 6, 78, 68, 45, 103, 134, 121, 126, 84, 51, 1],
        "scheduled lines": [5, 24, 15, 5, -1, -1, 28, -1, 15, 5]
      },
      {
        "weight":1,
        "nodes": [1, 75, 87, 11, 64, 123, 38, 41, 112, 91, 122, 130, 1],
        "scheduled lines": [-1, 5, -1, 5, 17, 25, -1, -1, -1, -1, -1]
      },
      {
        "weight":1,
        "nodes": [1, 77, 94, 86, 54, 57, 7, 113, 60, 100, 53, 32, 48, 82, 116, 81, 124, 74, 33, 15, 44, 1],
        "scheduled lines": [-1, -1, -1, -1, 5, -1, -1, -1, -1, 6, 5, -1, 5, 6, -1, -1, -1, -1, 6, -1]
      },
      {
        "weight":1,
        "nodes": [2, 99, 22, 5, 96, 90, 52, 35, 66, 110, 115, 2],
        "scheduled lines": [-1, 0, -1, -1, -1, -1, -1, -1, 20, 21]
      },
      {
        "weight":1,
        "nodes": [2, 24, 50, 132, 72, 102, 2],
        "scheduled lines": [-1, 0, 14, -1, -1]
      },
      {
        "weight":1,
        "nodes": [2, 93, 8, 65, 25, 69, 36, 23, 42, 107, 2],
        "scheduled lines": [0, -1, 0, 21, -1, -1, 20, 14, -1]
      },
      {
        "weight":1,
        "nodes": [2, 108, 73, 17, 114, 28, 18, 3, 13, 10, 95, 92, 55, 16, 80, 101, 109, 125, 2],
        "scheduled lines": [-1, -1, -1, -1, -1, 21, -1, 1, -1, -1, -1, -1, 19, -1, -1, -1, -1]
      }
    ]
  }
}